py_readonlyx/__init__.py
py_readonlyx/readonly.py
py_readonlyx-1.6.0.dist-info/licenses/LICENSE
py_readonlyx-1.6.0.dist-info/METADATA
py_readonlyx-1.6.0.dist-info/WHEEL
py_readonlyx-1.6.0.dist-info/top_level.txt
py_readonlyx-1.6.0.dist-info/RECORD
