Metadata-Version: 2.4
Name: py-readonlyx
Version: 1.6.0
Summary: Lightweight Python Read-Only Property Decorator
Home-page: https://github.com/firatmio/py-readonlyx
Author: firatmio
Author-email: firatmio <firattunaarslan@gmail.com>
License: Apache-2.0
Project-URL: Homepage, https://github.com/firatmio/py-readonlyx
Project-URL: Bug Tracker, https://github.com/firatmio/py-readonlyx/issues
Project-URL: Repository, https://github.com/firatmio/py-readonlyx
Project-URL: Documentation, https://github.com/firatmio/py-readonlyx#readme
Keywords: readonly,property,decorator,immutable,python
Classifier: Development Status :: 5 - Production/Stable
Classifier: Intended Audience :: Developers
Classifier: License :: OSI Approved :: Apache Software License
Classifier: Operating System :: OS Independent
Classifier: Programming Language :: Python :: 3
Classifier: Programming Language :: Python :: 3.8
Classifier: Programming Language :: Python :: 3.9
Classifier: Programming Language :: Python :: 3.10
Classifier: Programming Language :: Python :: 3.11
Classifier: Programming Language :: Python :: 3.12
Classifier: Topic :: Software Development :: Libraries :: Python Modules
Classifier: Topic :: Utilities
Requires-Python: >=3.8
License-File: LICENSE
Provides-Extra: dev
Requires-Dist: pytest>=6.0; extra == "dev"
Requires-Dist: pytest-cov; extra == "dev"
Requires-Dist: black; extra == "dev"
Requires-Dist: flake8; extra == "dev"
Dynamic: author
Dynamic: home-page
Dynamic: license-file
Dynamic: requires-python
